{
    "environment": "CartPole-v1",
    "discount_factor": 1.0,
    "epsilon_decay": 0.999,
    "k": 3000,
    "gaussian_width_rewards": 1.0,
    "training_seed": 1615744464,
    "testing_seed": 2387659052,
    "comments": "",
    "training_time": 100,
    "testing_time": 100,
    "training_rewards": [
        16.0,
        10.0,
        9.0,
        41.0,
        59.0,
        40.0,
        27.0,
        35.0,
        45.0,
        51.0,
        130.0,
        30.0,
        122.0,
        96.0,
        163.0,
        174.0,
        500.0,
        81.0,
        173.0,
        31.0,
        147.0,
        140.0,
        147.0,
        101.0,
        122.0,
        121.0,
        288.0,
        138.0,
        151.0,
        99.0,
        139.0,
        118.0,
        115.0,
        138.0,
        169.0,
        29.0,
        439.0,
        500.0,
        311.0,
        180.0,
        458.0,
        170.0,
        234.0,
        140.0,
        248.0,
        500.0,
        249.0,
        229.0,
        161.0,
        329.0,
        210.0,
        481.0,
        145.0,
        221.0,
        353.0,
        218.0,
        261.0,
        500.0,
        156.0,
        230.0,
        246.0,
        253.0,
        370.0,
        233.0,
        361.0,
        276.0,
        280.0,
        345.0,
        192.0,
        207.0,
        240.0,
        401.0,
        387.0,
        209.0,
        500.0,
        246.0,
        269.0,
        241.0,
        500.0,
        142.0,
        227.0,
        269.0,
        182.0,
        130.0,
        214.0,
        230.0,
        259.0,
        417.0,
        241.0,
        275.0,
        232.0,
        303.0,
        367.0,
        76.0,
        251.0,
        302.0,
        234.0,
        410.0,
        194.0,
        290.0,
        455.0
    ],
    "testing_rewards": [
        500.0,
        500.0,
        500.0,
        336.0,
        426.0,
        500.0,
        500.0,
        413.0,
        392.0,
        500.0,
        500.0,
        286.0,
        500.0,
        500.0,
        476.0,
        500.0,
        500.0,
        500.0,
        466.0,
        500.0,
        383.0,
        302.0,
        414.0,
        290.0,
        500.0,
        447.0,
        371.0,
        500.0,
        319.0,
        500.0,
        500.0,
        500.0,
        359.0,
        500.0,
        412.0,
        500.0,
        500.0,
        287.0,
        500.0,
        284.0,
        332.0,
        383.0,
        500.0,
        426.0,
        500.0,
        290.0,
        281.0,
        500.0,
        409.0,
        350.0,
        314.0,
        500.0,
        500.0,
        391.0,
        270.0,
        479.0,
        500.0,
        396.0,
        288.0,
        357.0,
        347.0,
        290.0,
        500.0,
        500.0,
        500.0,
        468.0,
        343.0,
        369.0,
        408.0,
        500.0,
        472.0,
        500.0,
        500.0,
        397.0,
        500.0,
        500.0,
        500.0,
        289.0,
        288.0,
        464.0,
        443.0,
        304.0,
        500.0,
        500.0,
        500.0,
        500.0,
        500.0,
        316.0,
        500.0,
        408.0,
        500.0,
        498.0,
        334.0,
        500.0,
        500.0,
        500.0,
        368.0,
        500.0,
        500.0,
        425.0,
        500.0
    ]
}