{
    "environment": "CartPole-v1",
    "discount_factor": 1.0,
    "epsilon_decay": 0.999,
    "k": 750,
    "gaussian_width_rewards": 0.5,
    "training_seed": 3615690266,
    "testing_seed": 898107312,
    "comments": "",
    "training_time": 100,
    "testing_time": 100,
    "training_rewards": [
        14.0,
        10.0,
        10.0,
        52.0,
        39.0,
        75.0,
        62.0,
        80.0,
        81.0,
        152.0,
        49.0,
        188.0,
        167.0,
        44.0,
        270.0,
        20.0,
        43.0,
        204.0,
        95.0,
        46.0,
        67.0,
        430.0,
        112.0,
        43.0,
        95.0,
        69.0,
        91.0,
        86.0,
        122.0,
        151.0,
        77.0,
        229.0,
        421.0,
        425.0,
        224.0,
        358.0,
        298.0,
        298.0,
        166.0,
        190.0,
        274.0,
        249.0,
        276.0,
        90.0,
        405.0,
        156.0,
        122.0,
        219.0,
        78.0,
        286.0,
        20.0,
        209.0,
        441.0,
        154.0,
        264.0,
        143.0,
        257.0,
        148.0,
        100.0,
        145.0,
        203.0,
        144.0,
        178.0,
        269.0,
        75.0,
        127.0,
        148.0,
        271.0,
        240.0,
        73.0,
        456.0,
        183.0,
        80.0,
        151.0,
        73.0,
        175.0,
        137.0,
        142.0,
        198.0,
        479.0,
        175.0,
        400.0,
        295.0,
        193.0,
        111.0,
        141.0,
        187.0,
        208.0,
        139.0,
        183.0,
        234.0,
        180.0,
        326.0,
        363.0,
        288.0,
        281.0,
        93.0,
        297.0,
        53.0,
        118.0,
        160.0
    ],
    "testing_rewards": [
        35.0,
        31.0,
        36.0,
        36.0,
        35.0,
        33.0,
        31.0,
        34.0,
        33.0,
        15.0,
        27.0,
        29.0,
        28.0,
        34.0,
        32.0,
        27.0,
        30.0,
        29.0,
        28.0,
        33.0,
        34.0,
        26.0,
        34.0,
        25.0,
        28.0,
        29.0,
        28.0,
        32.0,
        27.0,
        29.0,
        32.0,
        35.0,
        15.0,
        28.0,
        27.0,
        15.0,
        33.0,
        30.0,
        28.0,
        29.0,
        30.0,
        37.0,
        27.0,
        15.0,
        27.0,
        31.0,
        35.0,
        27.0,
        31.0,
        29.0,
        34.0,
        26.0,
        33.0,
        34.0,
        29.0,
        26.0,
        28.0,
        31.0,
        31.0,
        32.0,
        29.0,
        31.0,
        28.0,
        26.0,
        34.0,
        31.0,
        15.0,
        32.0,
        30.0,
        31.0,
        35.0,
        26.0,
        34.0,
        36.0,
        35.0,
        32.0,
        35.0,
        29.0,
        32.0,
        30.0,
        31.0,
        27.0,
        27.0,
        15.0,
        32.0,
        32.0,
        31.0,
        29.0,
        28.0,
        33.0,
        32.0,
        30.0,
        36.0,
        25.0,
        30.0,
        32.0,
        34.0,
        35.0,
        28.0,
        32.0,
        34.0
    ]
}