{
    "environment": "CartPole-v1",
    "discount_factor": 1.0,
    "epsilon_decay": 0.999,
    "k": 500,
    "gaussian_width_rewards": 0.5,
    "training_seed": 265270932,
    "testing_seed": 3718699606,
    "comments": "",
    "training_time": 100,
    "testing_time": 100,
    "training_rewards": [
        8.0,
        15.0,
        13.0,
        39.0,
        65.0,
        67.0,
        11.0,
        36.0,
        99.0,
        75.0,
        140.0,
        102.0,
        75.0,
        63.0,
        79.0,
        80.0,
        103.0,
        103.0,
        48.0,
        35.0,
        133.0,
        32.0,
        36.0,
        21.0,
        80.0,
        39.0,
        57.0,
        119.0,
        74.0,
        42.0,
        100.0,
        91.0,
        60.0,
        55.0,
        75.0,
        18.0,
        58.0,
        62.0,
        75.0,
        21.0,
        54.0,
        182.0,
        63.0,
        15.0,
        24.0,
        87.0,
        97.0,
        55.0,
        41.0,
        127.0,
        49.0,
        289.0,
        243.0,
        78.0,
        23.0,
        178.0,
        68.0,
        61.0,
        152.0,
        276.0,
        75.0,
        83.0,
        81.0,
        251.0,
        72.0,
        17.0,
        107.0,
        70.0,
        68.0,
        172.0,
        232.0,
        77.0,
        151.0,
        123.0,
        80.0,
        91.0,
        43.0,
        14.0,
        79.0,
        79.0,
        70.0,
        151.0,
        80.0,
        151.0,
        34.0,
        99.0,
        139.0,
        87.0,
        111.0,
        115.0,
        123.0,
        77.0,
        200.0,
        194.0,
        21.0,
        80.0,
        29.0,
        117.0,
        29.0,
        49.0,
        65.0
    ],
    "testing_rewards": [
        148.0,
        63.0,
        149.0,
        52.0,
        180.0,
        159.0,
        58.0,
        120.0,
        63.0,
        91.0,
        218.0,
        80.0,
        123.0,
        53.0,
        105.0,
        124.0,
        218.0,
        63.0,
        227.0,
        243.0,
        84.0,
        197.0,
        147.0,
        201.0,
        206.0,
        141.0,
        181.0,
        152.0,
        55.0,
        51.0,
        170.0,
        164.0,
        123.0,
        126.0,
        220.0,
        255.0,
        76.0,
        198.0,
        116.0,
        48.0,
        76.0,
        153.0,
        246.0,
        79.0,
        63.0,
        20.0,
        338.0,
        101.0,
        170.0,
        223.0,
        129.0,
        129.0,
        23.0,
        186.0,
        230.0,
        103.0,
        63.0,
        52.0,
        128.0,
        61.0,
        202.0,
        112.0,
        142.0,
        73.0,
        132.0,
        136.0,
        253.0,
        67.0,
        51.0,
        242.0,
        209.0,
        92.0,
        238.0,
        152.0,
        172.0,
        321.0,
        77.0,
        68.0,
        78.0,
        211.0,
        226.0,
        301.0,
        68.0,
        51.0,
        91.0,
        134.0,
        77.0,
        45.0,
        209.0,
        232.0,
        60.0,
        200.0,
        116.0,
        142.0,
        72.0,
        183.0,
        211.0,
        140.0,
        94.0,
        185.0,
        215.0
    ]
}