{
    "environment": "CartPole-v1",
    "discount_factor": 1.0,
    "epsilon_decay": 0.999,
    "k": 500,
    "gaussian_width_rewards": 0.1,
    "training_seed": 31847259,
    "testing_seed": 1760840903,
    "comments": "",
    "training_time": 100,
    "testing_time": 100,
    "training_rewards": [
        51.0,
        25.0,
        11.0,
        21.0,
        10.0,
        54.0,
        41.0,
        42.0,
        150.0,
        51.0,
        93.0,
        57.0,
        21.0,
        179.0,
        165.0,
        61.0,
        77.0,
        128.0,
        15.0,
        71.0,
        43.0,
        58.0,
        35.0,
        75.0,
        26.0,
        63.0,
        83.0,
        89.0,
        258.0,
        127.0,
        62.0,
        326.0,
        138.0,
        189.0,
        155.0,
        314.0,
        290.0,
        101.0,
        104.0,
        89.0,
        300.0,
        16.0,
        263.0,
        151.0,
        52.0,
        118.0,
        252.0,
        296.0,
        241.0,
        158.0,
        221.0,
        483.0,
        194.0,
        94.0,
        92.0,
        247.0,
        260.0,
        181.0,
        101.0,
        264.0,
        89.0,
        142.0,
        201.0,
        96.0,
        118.0,
        196.0,
        92.0,
        324.0,
        229.0,
        83.0,
        112.0,
        144.0,
        213.0,
        280.0,
        208.0,
        152.0,
        203.0,
        405.0,
        194.0,
        77.0,
        121.0,
        26.0,
        75.0,
        322.0,
        266.0,
        465.0,
        131.0,
        158.0,
        117.0,
        190.0,
        188.0,
        308.0,
        151.0,
        26.0,
        58.0,
        177.0,
        495.0,
        62.0,
        166.0,
        237.0,
        238.0
    ],
    "testing_rewards": [
        500.0,
        202.0,
        266.0,
        54.0,
        153.0,
        183.0,
        500.0,
        126.0,
        180.0,
        283.0,
        158.0,
        122.0,
        112.0,
        142.0,
        500.0,
        243.0,
        500.0,
        423.0,
        500.0,
        108.0,
        290.0,
        484.0,
        298.0,
        488.0,
        308.0,
        180.0,
        201.0,
        117.0,
        268.0,
        455.0,
        467.0,
        191.0,
        378.0,
        102.0,
        201.0,
        352.0,
        176.0,
        500.0,
        185.0,
        25.0,
        167.0,
        371.0,
        500.0,
        483.0,
        316.0,
        500.0,
        210.0,
        353.0,
        500.0,
        228.0,
        214.0,
        164.0,
        174.0,
        144.0,
        198.0,
        95.0,
        207.0,
        500.0,
        500.0,
        500.0,
        186.0,
        265.0,
        199.0,
        500.0,
        159.0,
        228.0,
        71.0,
        349.0,
        197.0,
        149.0,
        369.0,
        404.0,
        500.0,
        323.0,
        500.0,
        170.0,
        273.0,
        216.0,
        187.0,
        134.0,
        500.0,
        296.0,
        183.0,
        407.0,
        500.0,
        262.0,
        365.0,
        194.0,
        136.0,
        128.0,
        125.0,
        199.0,
        500.0,
        274.0,
        190.0,
        118.0,
        289.0,
        260.0,
        145.0,
        500.0,
        186.0
    ]
}