{
    "environment": "CartPole-v1",
    "discount_factor": 1.0,
    "epsilon_decay": 0.999,
    "k": 500,
    "gaussian_width_rewards": 3.0,
    "training_seed": 3623471966,
    "testing_seed": 3593070307,
    "comments": "",
    "training_time": 100,
    "testing_time": 100,
    "training_rewards": [
        106.0,
        22.0,
        9.0,
        109.0,
        182.0,
        71.0,
        49.0,
        79.0,
        34.0,
        368.0,
        33.0,
        72.0,
        56.0,
        64.0,
        53.0,
        113.0,
        132.0,
        119.0,
        161.0,
        107.0,
        98.0,
        73.0,
        140.0,
        174.0,
        258.0,
        185.0,
        183.0,
        97.0,
        97.0,
        119.0,
        116.0,
        121.0,
        167.0,
        80.0,
        70.0,
        87.0,
        61.0,
        117.0,
        51.0,
        70.0,
        58.0,
        65.0,
        148.0,
        74.0,
        54.0,
        122.0,
        108.0,
        54.0,
        70.0,
        114.0,
        84.0,
        55.0,
        159.0,
        66.0,
        184.0,
        65.0,
        54.0,
        176.0,
        73.0,
        105.0,
        407.0,
        145.0,
        149.0,
        123.0,
        143.0,
        132.0,
        173.0,
        123.0,
        224.0,
        117.0,
        141.0,
        133.0,
        133.0,
        112.0,
        123.0,
        163.0,
        151.0,
        424.0,
        154.0,
        283.0,
        70.0,
        111.0,
        118.0,
        264.0,
        103.0,
        249.0,
        36.0,
        112.0,
        121.0,
        39.0,
        41.0,
        135.0,
        30.0,
        500.0,
        34.0,
        56.0,
        60.0,
        100.0,
        500.0,
        202.0,
        225.0
    ],
    "testing_rewards": [
        359.0,
        500.0,
        500.0,
        500.0,
        205.0,
        264.0,
        500.0,
        228.0,
        326.0,
        500.0,
        500.0,
        500.0,
        193.0,
        500.0,
        500.0,
        500.0,
        500.0,
        500.0,
        222.0,
        500.0,
        500.0,
        500.0,
        500.0,
        500.0,
        500.0,
        500.0,
        500.0,
        500.0,
        500.0,
        500.0,
        500.0,
        265.0,
        500.0,
        500.0,
        500.0,
        500.0,
        500.0,
        500.0,
        254.0,
        500.0,
        500.0,
        500.0,
        500.0,
        500.0,
        500.0,
        500.0,
        500.0,
        500.0,
        170.0,
        193.0,
        500.0,
        500.0,
        500.0,
        331.0,
        500.0,
        500.0,
        500.0,
        500.0,
        262.0,
        500.0,
        500.0,
        500.0,
        500.0,
        222.0,
        500.0,
        500.0,
        500.0,
        500.0,
        500.0,
        253.0,
        500.0,
        500.0,
        500.0,
        282.0,
        500.0,
        236.0,
        500.0,
        500.0,
        500.0,
        172.0,
        500.0,
        226.0,
        500.0,
        500.0,
        252.0,
        500.0,
        500.0,
        203.0,
        500.0,
        500.0,
        218.0,
        500.0,
        500.0,
        500.0,
        500.0,
        500.0,
        500.0,
        500.0,
        500.0,
        500.0,
        500.0
    ]
}