{
    "environment": "CartPole-v1",
    "discount_factor": 1.0,
    "epsilon_decay": 0.999,
    "k": 500,
    "gaussian_width_rewards": 15.0,
    "training_seed": 354889275,
    "testing_seed": 2210727781,
    "comments": "",
    "training_time": 100,
    "testing_time": 100,
    "training_rewards": [
        21.0,
        15.0,
        8.0,
        39.0,
        67.0,
        57.0,
        81.0,
        50.0,
        55.0,
        117.0,
        58.0,
        46.0,
        51.0,
        53.0,
        43.0,
        46.0,
        45.0,
        54.0,
        56.0,
        59.0,
        63.0,
        162.0,
        41.0,
        128.0,
        37.0,
        65.0,
        33.0,
        55.0,
        73.0,
        48.0,
        57.0,
        32.0,
        29.0,
        121.0,
        77.0,
        57.0,
        68.0,
        68.0,
        47.0,
        46.0,
        78.0,
        97.0,
        108.0,
        288.0,
        106.0,
        60.0,
        84.0,
        60.0,
        36.0,
        52.0,
        44.0,
        68.0,
        55.0,
        52.0,
        54.0,
        56.0,
        58.0,
        121.0,
        79.0,
        228.0,
        59.0,
        45.0,
        161.0,
        157.0,
        47.0,
        93.0,
        47.0,
        85.0,
        91.0,
        89.0,
        63.0,
        54.0,
        125.0,
        58.0,
        97.0,
        63.0,
        128.0,
        87.0,
        99.0,
        86.0,
        84.0,
        96.0,
        68.0,
        71.0,
        65.0,
        54.0,
        61.0,
        60.0,
        61.0,
        58.0,
        100.0,
        46.0,
        43.0,
        48.0,
        71.0,
        103.0,
        182.0,
        54.0,
        71.0,
        62.0,
        57.0
    ],
    "testing_rewards": [
        192.0,
        386.0,
        103.0,
        108.0,
        264.0,
        155.0,
        82.0,
        51.0,
        61.0,
        50.0,
        69.0,
        259.0,
        94.0,
        68.0,
        132.0,
        246.0,
        101.0,
        445.0,
        115.0,
        50.0,
        48.0,
        118.0,
        267.0,
        88.0,
        100.0,
        357.0,
        187.0,
        205.0,
        67.0,
        71.0,
        57.0,
        322.0,
        120.0,
        60.0,
        80.0,
        82.0,
        204.0,
        64.0,
        72.0,
        97.0,
        65.0,
        76.0,
        151.0,
        64.0,
        80.0,
        58.0,
        56.0,
        132.0,
        70.0,
        102.0,
        60.0,
        118.0,
        122.0,
        71.0,
        500.0,
        67.0,
        91.0,
        252.0,
        95.0,
        320.0,
        368.0,
        500.0,
        70.0,
        70.0,
        67.0,
        83.0,
        250.0,
        70.0,
        126.0,
        80.0,
        66.0,
        182.0,
        162.0,
        129.0,
        105.0,
        279.0,
        321.0,
        281.0,
        77.0,
        500.0,
        365.0,
        242.0,
        70.0,
        500.0,
        55.0,
        177.0,
        500.0,
        110.0,
        500.0,
        75.0,
        500.0,
        462.0,
        302.0,
        69.0,
        500.0,
        255.0,
        379.0,
        317.0,
        79.0,
        95.0,
        118.0
    ]
}