{
    "environment": "CartPole-v1",
    "discount_factor": 1.0,
    "epsilon_decay": 0.999,
    "k": 500,
    "gaussian_width_rewards": 2.5,
    "training_seed": 126665316,
    "testing_seed": 2839055567,
    "comments": "",
    "training_time": 100,
    "testing_time": 100,
    "training_rewards": [
        20.0,
        14.0,
        8.0,
        35.0,
        87.0,
        29.0,
        80.0,
        107.0,
        97.0,
        324.0,
        500.0,
        171.0,
        100.0,
        95.0,
        256.0,
        86.0,
        254.0,
        123.0,
        98.0,
        137.0,
        133.0,
        164.0,
        141.0,
        164.0,
        175.0,
        193.0,
        185.0,
        129.0,
        190.0,
        173.0,
        150.0,
        151.0,
        135.0,
        157.0,
        129.0,
        155.0,
        163.0,
        141.0,
        165.0,
        143.0,
        160.0,
        156.0,
        142.0,
        187.0,
        140.0,
        151.0,
        159.0,
        154.0,
        166.0,
        176.0,
        175.0,
        154.0,
        161.0,
        175.0,
        161.0,
        159.0,
        161.0,
        170.0,
        166.0,
        188.0,
        184.0,
        184.0,
        148.0,
        163.0,
        176.0,
        155.0,
        145.0,
        162.0,
        152.0,
        155.0,
        161.0,
        139.0,
        167.0,
        161.0,
        170.0,
        190.0,
        161.0,
        154.0,
        162.0,
        199.0,
        143.0,
        169.0,
        146.0,
        170.0,
        150.0,
        192.0,
        149.0,
        156.0,
        165.0,
        156.0,
        177.0,
        165.0,
        164.0,
        172.0,
        154.0,
        148.0,
        159.0,
        153.0,
        151.0,
        148.0,
        156.0
    ],
    "testing_rewards": [
        142.0,
        181.0,
        185.0,
        500.0,
        500.0,
        500.0,
        500.0,
        500.0,
        171.0,
        500.0,
        173.0,
        193.0,
        500.0,
        129.0,
        186.0,
        176.0,
        191.0,
        165.0,
        500.0,
        124.0,
        500.0,
        145.0,
        500.0,
        149.0,
        175.0,
        198.0,
        500.0,
        500.0,
        188.0,
        500.0,
        188.0,
        500.0,
        186.0,
        173.0,
        500.0,
        500.0,
        144.0,
        122.0,
        500.0,
        500.0,
        500.0,
        500.0,
        176.0,
        500.0,
        287.0,
        500.0,
        500.0,
        194.0,
        500.0,
        170.0,
        160.0,
        169.0,
        500.0,
        500.0,
        136.0,
        500.0,
        164.0,
        500.0,
        500.0,
        500.0,
        127.0,
        500.0,
        345.0,
        195.0,
        500.0,
        120.0,
        172.0,
        500.0,
        131.0,
        500.0,
        131.0,
        500.0,
        169.0,
        126.0,
        123.0,
        151.0,
        163.0,
        500.0,
        340.0,
        168.0,
        330.0,
        145.0,
        117.0,
        500.0,
        149.0,
        500.0,
        500.0,
        500.0,
        500.0,
        500.0,
        184.0,
        296.0,
        500.0,
        500.0,
        205.0,
        500.0,
        500.0,
        158.0,
        219.0,
        500.0,
        136.0
    ]
}