{
    "environment": "CartPole-v1",
    "discount_factor": 1,
    "k": 3000,
    "gaussian_width_rewards": 0.5,
    "seed": 492668817,
    "comments": "",
    "training_time": 100,
    "testing_time": 100,
    "training_rewards": [
        9.0,
        9.0,
        33.0,
        23.0,
        89.0,
        195.0,
        81.0,
        93.0,
        69.0,
        120.0,
        39.0,
        72.0,
        84.0,
        86.0,
        54.0,
        69.0,
        95.0,
        123.0,
        93.0,
        229.0,
        54.0,
        76.0,
        35.0,
        94.0,
        143.0,
        59.0,
        136.0,
        67.0,
        64.0,
        63.0,
        68.0,
        80.0,
        65.0,
        71.0,
        103.0,
        261.0,
        197.0,
        120.0,
        69.0,
        169.0,
        86.0,
        500.0,
        79.0,
        175.0,
        97.0,
        155.0,
        127.0,
        127.0,
        110.0,
        56.0,
        133.0,
        125.0,
        201.0,
        165.0,
        105.0,
        79.0,
        195.0,
        136.0,
        194.0,
        126.0,
        71.0,
        256.0,
        62.0,
        280.0,
        56.0,
        190.0,
        116.0,
        245.0,
        183.0,
        98.0,
        128.0,
        166.0,
        82.0,
        481.0,
        146.0,
        57.0,
        139.0,
        195.0,
        148.0,
        85.0,
        140.0,
        224.0,
        115.0,
        308.0,
        199.0,
        134.0,
        102.0,
        108.0,
        156.0,
        99.0,
        110.0,
        115.0,
        240.0,
        123.0,
        198.0,
        108.0,
        348.0,
        322.0,
        380.0,
        231.0,
        271.0
    ],
    "testing_rewards": [
        179.0,
        161.0,
        214.0,
        181.0,
        206.0,
        180.0,
        166.0,
        199.0,
        178.0,
        242.0,
        330.0,
        208.0,
        194.0,
        143.0,
        162.0,
        218.0,
        182.0,
        222.0,
        185.0,
        234.0,
        166.0,
        204.0,
        217.0,
        140.0,
        170.0,
        245.0,
        183.0,
        275.0,
        194.0,
        177.0,
        175.0,
        198.0,
        229.0,
        178.0,
        111.0,
        230.0,
        130.0,
        155.0,
        134.0,
        144.0,
        149.0,
        134.0,
        209.0,
        291.0,
        235.0,
        175.0,
        184.0,
        175.0,
        241.0,
        220.0,
        165.0,
        185.0,
        142.0,
        242.0,
        259.0,
        185.0,
        122.0,
        205.0,
        417.0,
        162.0,
        289.0,
        133.0,
        222.0,
        260.0,
        180.0,
        172.0,
        150.0,
        199.0,
        182.0,
        219.0,
        171.0,
        169.0,
        312.0,
        161.0,
        209.0,
        172.0,
        168.0,
        150.0,
        172.0,
        169.0,
        221.0,
        182.0,
        129.0,
        217.0,
        154.0,
        201.0,
        148.0,
        242.0,
        171.0,
        154.0,
        209.0,
        335.0,
        141.0,
        141.0,
        183.0,
        193.0,
        205.0,
        227.0,
        199.0,
        197.0,
        208.0
    ]
}