{
    "environment": "CartPole-v1",
    "discount_factor": 1.0,
    "epsilon_decay": 0.999,
    "k": 3500,
    "gaussian_width_rewards": 0.5,
    "training_seed": 2489786708,
    "testing_seed": 1208475362,
    "comments": "Weighted k-means. Softmax t=50. Linear regression. Error treshold 0.01.",
    "training_time": 100,
    "testing_time": 100,
    "training_rewards": [
        17.0,
        11.0,
        10.0,
        40.0,
        26.0,
        28.0,
        121.0,
        68.0,
        75.0,
        34.0,
        121.0,
        162.0,
        482.0,
        271.0,
        143.0,
        235.0,
        500.0,
        500.0,
        277.0,
        381.0,
        329.0,
        138.0,
        125.0,
        138.0,
        183.0,
        143.0,
        284.0,
        266.0,
        308.0,
        150.0,
        475.0,
        193.0,
        120.0,
        159.0,
        202.0,
        295.0,
        150.0,
        135.0,
        233.0,
        370.0,
        500.0,
        194.0,
        156.0,
        245.0,
        353.0,
        456.0,
        159.0,
        492.0,
        216.0,
        226.0,
        320.0,
        219.0,
        304.0,
        500.0,
        86.0,
        273.0,
        93.0,
        291.0,
        490.0,
        500.0,
        118.0,
        331.0,
        109.0,
        344.0,
        177.0,
        153.0,
        168.0,
        500.0,
        500.0,
        336.0,
        252.0,
        447.0,
        246.0,
        150.0,
        435.0,
        96.0,
        500.0,
        260.0,
        500.0,
        392.0,
        273.0,
        500.0,
        219.0,
        242.0,
        101.0,
        233.0,
        500.0,
        118.0,
        500.0,
        425.0,
        294.0,
        191.0,
        330.0,
        88.0,
        159.0,
        500.0,
        192.0,
        247.0,
        500.0,
        237.0,
        392.0
    ],
    "testing_rewards": [
        142.0,
        137.0,
        184.0,
        163.0,
        242.0,
        189.0,
        141.0,
        151.0,
        183.0,
        201.0,
        171.0,
        23.0,
        252.0,
        173.0,
        148.0,
        222.0,
        187.0,
        172.0,
        155.0,
        231.0,
        500.0,
        134.0,
        196.0,
        56.0,
        131.0,
        25.0,
        190.0,
        189.0,
        133.0,
        177.0,
        188.0,
        148.0,
        127.0,
        262.0,
        232.0,
        192.0,
        25.0,
        147.0,
        319.0,
        189.0,
        174.0,
        500.0,
        153.0,
        189.0,
        229.0,
        185.0,
        190.0,
        144.0,
        193.0,
        213.0,
        175.0,
        20.0,
        177.0,
        500.0,
        22.0,
        136.0,
        224.0,
        163.0,
        165.0,
        342.0,
        178.0,
        143.0,
        193.0,
        314.0,
        202.0,
        500.0,
        325.0,
        203.0,
        22.0,
        192.0,
        208.0,
        190.0,
        224.0,
        23.0,
        294.0,
        182.0,
        368.0,
        214.0,
        500.0,
        168.0,
        424.0,
        146.0,
        172.0,
        195.0,
        197.0,
        173.0,
        152.0,
        191.0,
        187.0,
        171.0,
        197.0,
        143.0,
        236.0,
        202.0,
        271.0,
        214.0,
        132.0,
        193.0,
        213.0,
        179.0,
        193.0
    ]
}