{
    "environment": "CartPole-v1",
    "discount_factor": 1.0,
    "epsilon_decay": 0.999,
    "k": 3000,
    "gaussian_width_rewards": 2.5,
    "training_seed": 3715786601,
    "testing_seed": 3225327580,
    "comments": "",
    "training_time": 100,
    "testing_time": 100,
    "training_rewards": [
        25.0,
        14.0,
        9.0,
        54.0,
        45.0,
        106.0,
        27.0,
        30.0,
        47.0,
        52.0,
        103.0,
        103.0,
        247.0,
        135.0,
        90.0,
        156.0,
        102.0,
        100.0,
        67.0,
        92.0,
        76.0,
        81.0,
        94.0,
        112.0,
        76.0,
        126.0,
        159.0,
        500.0,
        500.0,
        500.0,
        222.0,
        153.0,
        155.0,
        120.0,
        123.0,
        111.0,
        149.0,
        121.0,
        123.0,
        119.0,
        168.0,
        166.0,
        159.0,
        149.0,
        166.0,
        146.0,
        171.0,
        149.0,
        164.0,
        160.0,
        155.0,
        148.0,
        157.0,
        152.0,
        155.0,
        161.0,
        148.0,
        154.0,
        186.0,
        182.0,
        160.0,
        190.0,
        167.0,
        159.0,
        140.0,
        162.0,
        155.0,
        134.0,
        155.0,
        169.0,
        152.0,
        142.0,
        135.0,
        169.0,
        159.0,
        146.0,
        140.0,
        172.0,
        178.0,
        159.0,
        141.0,
        144.0,
        197.0,
        161.0,
        172.0,
        221.0,
        163.0,
        203.0,
        167.0,
        180.0,
        166.0,
        177.0,
        167.0,
        155.0,
        187.0,
        224.0,
        194.0,
        159.0,
        197.0,
        178.0,
        218.0
    ],
    "testing_rewards": [
        134.0,
        145.0,
        500.0,
        500.0,
        500.0,
        213.0,
        198.0,
        500.0,
        500.0,
        136.0,
        500.0,
        163.0,
        500.0,
        154.0,
        500.0,
        500.0,
        500.0,
        500.0,
        154.0,
        500.0,
        500.0,
        162.0,
        216.0,
        500.0,
        206.0,
        500.0,
        500.0,
        500.0,
        152.0,
        177.0,
        239.0,
        500.0,
        500.0,
        157.0,
        158.0,
        500.0,
        500.0,
        500.0,
        500.0,
        500.0,
        161.0,
        172.0,
        175.0,
        500.0,
        500.0,
        500.0,
        500.0,
        198.0,
        500.0,
        500.0,
        500.0,
        209.0,
        500.0,
        500.0,
        500.0,
        500.0,
        500.0,
        233.0,
        500.0,
        500.0,
        500.0,
        500.0,
        155.0,
        167.0,
        500.0,
        186.0,
        500.0,
        500.0,
        147.0,
        217.0,
        161.0,
        137.0,
        500.0,
        500.0,
        500.0,
        500.0,
        180.0,
        152.0,
        500.0,
        500.0,
        500.0,
        500.0,
        500.0,
        156.0,
        500.0,
        168.0,
        500.0,
        500.0,
        500.0,
        192.0,
        135.0,
        153.0,
        500.0,
        164.0,
        183.0,
        500.0,
        154.0,
        155.0,
        500.0,
        183.0,
        150.0
    ]
}