{
    "environment": "CartPole-v1",
    "discount_factor": 1.0,
    "epsilon_decay": 0.999,
    "k": 500,
    "gaussian_width_rewards": 0.5,
    "training_seed": 838200331,
    "testing_seed": 1972765049,
    "comments": "",
    "training_time": 100,
    "testing_time": 100,
    "training_rewards": [
        22.0,
        11.0,
        9.0,
        58.0,
        44.0,
        37.0,
        51.0,
        25.0,
        58.0,
        49.0,
        39.0,
        81.0,
        31.0,
        41.0,
        79.0,
        53.0,
        180.0,
        71.0,
        75.0,
        62.0,
        114.0,
        193.0,
        77.0,
        45.0,
        72.0,
        158.0,
        170.0,
        123.0,
        115.0,
        138.0,
        222.0,
        189.0,
        85.0,
        145.0,
        195.0,
        75.0,
        88.0,
        153.0,
        95.0,
        88.0,
        183.0,
        287.0,
        161.0,
        67.0,
        109.0,
        96.0,
        154.0,
        72.0,
        99.0,
        180.0,
        111.0,
        230.0,
        73.0,
        140.0,
        100.0,
        102.0,
        169.0,
        168.0,
        187.0,
        232.0,
        154.0,
        52.0,
        199.0,
        145.0,
        308.0,
        88.0,
        143.0,
        392.0,
        131.0,
        199.0,
        34.0,
        326.0,
        87.0,
        137.0,
        112.0,
        379.0,
        271.0,
        17.0,
        12.0,
        193.0,
        79.0,
        77.0,
        40.0,
        168.0,
        228.0,
        205.0,
        500.0,
        30.0,
        12.0,
        88.0,
        145.0,
        108.0,
        67.0,
        222.0,
        53.0,
        15.0,
        49.0,
        59.0,
        468.0,
        320.0,
        53.0
    ],
    "testing_rewards": [
        186.0,
        270.0,
        110.0,
        119.0,
        129.0,
        120.0,
        456.0,
        115.0,
        145.0,
        150.0,
        179.0,
        118.0,
        245.0,
        119.0,
        254.0,
        348.0,
        136.0,
        442.0,
        271.0,
        124.0,
        145.0,
        336.0,
        126.0,
        111.0,
        150.0,
        192.0,
        120.0,
        297.0,
        463.0,
        166.0,
        144.0,
        203.0,
        104.0,
        310.0,
        153.0,
        274.0,
        172.0,
        145.0,
        288.0,
        286.0,
        140.0,
        110.0,
        116.0,
        131.0,
        151.0,
        143.0,
        148.0,
        141.0,
        366.0,
        156.0,
        126.0,
        151.0,
        271.0,
        128.0,
        144.0,
        376.0,
        120.0,
        151.0,
        443.0,
        232.0,
        136.0,
        222.0,
        407.0,
        437.0,
        182.0,
        421.0,
        134.0,
        153.0,
        154.0,
        324.0,
        124.0,
        157.0,
        134.0,
        137.0,
        166.0,
        129.0,
        154.0,
        276.0,
        338.0,
        127.0,
        164.0,
        159.0,
        132.0,
        116.0,
        288.0,
        392.0,
        145.0,
        119.0,
        153.0,
        111.0,
        155.0,
        127.0,
        124.0,
        500.0,
        114.0,
        154.0,
        112.0,
        140.0,
        122.0,
        141.0,
        124.0
    ]
}