{
    "environment": "CartPole-v1",
    "discount_factor": 1.0,
    "epsilon_decay": 0.999,
    "k": 500,
    "gaussian_width_rewards": 0.3,
    "training_seed": 1580812534,
    "testing_seed": 2488595121,
    "comments": "",
    "training_time": 100,
    "testing_time": 100,
    "training_rewards": [
        19.0,
        9.0,
        10.0,
        120.0,
        58.0,
        255.0,
        500.0,
        111.0,
        282.0,
        186.0,
        417.0,
        160.0,
        333.0,
        130.0,
        500.0,
        204.0,
        392.0,
        149.0,
        160.0,
        215.0,
        74.0,
        157.0,
        161.0,
        127.0,
        198.0,
        176.0,
        249.0,
        289.0,
        134.0,
        155.0,
        92.0,
        178.0,
        215.0,
        176.0,
        242.0,
        270.0,
        500.0,
        162.0,
        235.0,
        290.0,
        49.0,
        147.0,
        331.0,
        181.0,
        147.0,
        211.0,
        159.0,
        197.0,
        190.0,
        141.0,
        224.0,
        316.0,
        190.0,
        500.0,
        146.0,
        355.0,
        369.0,
        91.0,
        124.0,
        472.0,
        191.0,
        331.0,
        500.0,
        500.0,
        127.0,
        249.0,
        369.0,
        90.0,
        500.0,
        87.0,
        132.0,
        65.0,
        199.0,
        84.0,
        481.0,
        168.0,
        176.0,
        419.0,
        375.0,
        259.0,
        391.0,
        500.0,
        353.0,
        139.0,
        323.0,
        71.0,
        300.0,
        445.0,
        192.0,
        254.0,
        356.0,
        319.0,
        410.0,
        354.0,
        181.0,
        185.0,
        165.0,
        288.0,
        431.0,
        240.0,
        336.0
    ],
    "testing_rewards": [
        500.0,
        500.0,
        500.0,
        193.0,
        392.0,
        144.0,
        500.0,
        138.0,
        500.0,
        126.0,
        132.0,
        500.0,
        500.0,
        145.0,
        500.0,
        500.0,
        182.0,
        500.0,
        335.0,
        500.0,
        500.0,
        500.0,
        500.0,
        500.0,
        500.0,
        500.0,
        500.0,
        173.0,
        500.0,
        500.0,
        500.0,
        500.0,
        148.0,
        500.0,
        148.0,
        326.0,
        500.0,
        500.0,
        148.0,
        157.0,
        500.0,
        500.0,
        500.0,
        500.0,
        500.0,
        500.0,
        161.0,
        144.0,
        500.0,
        120.0,
        98.0,
        500.0,
        500.0,
        500.0,
        500.0,
        306.0,
        142.0,
        500.0,
        116.0,
        500.0,
        500.0,
        500.0,
        148.0,
        500.0,
        500.0,
        500.0,
        500.0,
        500.0,
        120.0,
        500.0,
        500.0,
        462.0,
        500.0,
        500.0,
        500.0,
        500.0,
        500.0,
        500.0,
        500.0,
        500.0,
        500.0,
        500.0,
        500.0,
        500.0,
        95.0,
        500.0,
        500.0,
        500.0,
        500.0,
        500.0,
        500.0,
        500.0,
        129.0,
        429.0,
        500.0,
        136.0,
        500.0,
        500.0,
        500.0,
        500.0,
        500.0
    ]
}