{
    "environment": "CartPole-v1",
    "discount_factor": 1.0,
    "epsilon_decay": 0.999,
    "k": 2500,
    "gaussian_width_rewards": 0.5,
    "training_seed": 266728360,
    "testing_seed": 2880760047,
    "comments": "",
    "training_time": 100,
    "testing_time": 100,
    "training_rewards": [
        21.0,
        23.0,
        10.0,
        9.0,
        18.0,
        46.0,
        57.0,
        159.0,
        49.0,
        46.0,
        53.0,
        58.0,
        46.0,
        51.0,
        40.0,
        53.0,
        50.0,
        78.0,
        49.0,
        71.0,
        45.0,
        65.0,
        42.0,
        73.0,
        60.0,
        124.0,
        53.0,
        190.0,
        75.0,
        57.0,
        243.0,
        92.0,
        108.0,
        82.0,
        65.0,
        64.0,
        51.0,
        48.0,
        132.0,
        139.0,
        147.0,
        100.0,
        50.0,
        124.0,
        73.0,
        71.0,
        52.0,
        165.0,
        19.0,
        141.0,
        95.0,
        145.0,
        186.0,
        93.0,
        109.0,
        240.0,
        177.0,
        417.0,
        419.0,
        21.0,
        15.0,
        254.0,
        13.0,
        272.0,
        96.0,
        353.0,
        217.0,
        136.0,
        198.0,
        14.0,
        178.0,
        11.0,
        184.0,
        191.0,
        15.0,
        199.0,
        21.0,
        500.0,
        246.0,
        55.0,
        169.0,
        224.0,
        347.0,
        134.0,
        151.0,
        308.0,
        314.0,
        257.0,
        167.0,
        48.0,
        42.0,
        377.0,
        207.0,
        402.0,
        12.0,
        251.0,
        27.0,
        201.0,
        324.0,
        154.0,
        180.0
    ],
    "testing_rewards": [
        148.0,
        132.0,
        46.0,
        197.0,
        150.0,
        208.0,
        159.0,
        207.0,
        144.0,
        195.0,
        158.0,
        205.0,
        189.0,
        163.0,
        162.0,
        138.0,
        156.0,
        146.0,
        44.0,
        210.0,
        143.0,
        154.0,
        154.0,
        196.0,
        156.0,
        200.0,
        196.0,
        194.0,
        197.0,
        217.0,
        130.0,
        183.0,
        194.0,
        144.0,
        45.0,
        144.0,
        231.0,
        15.0,
        201.0,
        156.0,
        158.0,
        236.0,
        49.0,
        150.0,
        181.0,
        144.0,
        15.0,
        206.0,
        136.0,
        189.0,
        128.0,
        171.0,
        240.0,
        16.0,
        201.0,
        195.0,
        219.0,
        170.0,
        182.0,
        225.0,
        245.0,
        156.0,
        268.0,
        160.0,
        235.0,
        45.0,
        158.0,
        147.0,
        160.0,
        195.0,
        15.0,
        144.0,
        190.0,
        51.0,
        223.0,
        172.0,
        234.0,
        15.0,
        15.0,
        152.0,
        146.0,
        158.0,
        140.0,
        15.0,
        235.0,
        162.0,
        248.0,
        227.0,
        173.0,
        213.0,
        195.0,
        189.0,
        206.0,
        166.0,
        154.0,
        215.0,
        15.0,
        186.0,
        152.0,
        198.0,
        238.0
    ]
}