{
    "environment": "CartPole-v1",
    "discount_factor": 1.0,
    "epsilon_decay": 0.999,
    "k": 2500,
    "gaussian_width_rewards": 0.5,
    "training_seed": 3205275257,
    "testing_seed": 1568373057,
    "comments": "",
    "training_time": 100,
    "testing_time": 100,
    "training_rewards": [
        11.0,
        14.0,
        11.0,
        16.0,
        34.0,
        114.0,
        59.0,
        87.0,
        113.0,
        105.0,
        77.0,
        165.0,
        76.0,
        283.0,
        500.0,
        153.0,
        159.0,
        165.0,
        153.0,
        302.0,
        290.0,
        331.0,
        141.0,
        122.0,
        167.0,
        139.0,
        144.0,
        225.0,
        500.0,
        194.0,
        172.0,
        136.0,
        187.0,
        262.0,
        172.0,
        174.0,
        187.0,
        128.0,
        174.0,
        304.0,
        115.0,
        221.0,
        180.0,
        200.0,
        148.0,
        223.0,
        263.0,
        185.0,
        418.0,
        109.0,
        177.0,
        138.0,
        112.0,
        305.0,
        100.0,
        110.0,
        121.0,
        137.0,
        84.0,
        138.0,
        155.0,
        194.0,
        101.0,
        121.0,
        169.0,
        123.0,
        157.0,
        138.0,
        218.0,
        210.0,
        185.0,
        100.0,
        93.0,
        91.0,
        151.0,
        100.0,
        163.0,
        127.0,
        82.0,
        65.0,
        199.0,
        132.0,
        258.0,
        179.0,
        241.0,
        110.0,
        290.0,
        106.0,
        133.0,
        132.0,
        91.0,
        111.0,
        108.0,
        155.0,
        102.0,
        97.0,
        216.0,
        80.0,
        92.0,
        179.0,
        135.0
    ],
    "testing_rewards": [
        500.0,
        166.0,
        150.0,
        158.0,
        164.0,
        158.0,
        162.0,
        500.0,
        156.0,
        500.0,
        175.0,
        166.0,
        156.0,
        172.0,
        500.0,
        154.0,
        500.0,
        164.0,
        500.0,
        500.0,
        160.0,
        500.0,
        500.0,
        500.0,
        158.0,
        500.0,
        150.0,
        166.0,
        169.0,
        500.0,
        168.0,
        159.0,
        144.0,
        169.0,
        500.0,
        156.0,
        500.0,
        500.0,
        154.0,
        162.0,
        170.0,
        166.0,
        162.0,
        168.0,
        160.0,
        164.0,
        162.0,
        160.0,
        166.0,
        148.0,
        500.0,
        151.0,
        152.0,
        500.0,
        500.0,
        165.0,
        166.0,
        166.0,
        166.0,
        500.0,
        500.0,
        500.0,
        500.0,
        500.0,
        154.0,
        500.0,
        152.0,
        164.0,
        500.0,
        500.0,
        500.0,
        500.0,
        439.0,
        500.0,
        500.0,
        500.0,
        154.0,
        162.0,
        150.0,
        500.0,
        152.0,
        500.0,
        158.0,
        164.0,
        162.0,
        166.0,
        162.0,
        160.0,
        150.0,
        500.0,
        164.0,
        500.0,
        154.0,
        500.0,
        162.0,
        156.0,
        500.0,
        500.0,
        500.0,
        500.0,
        500.0
    ]
}