{
    "environment": "CartPole-v1",
    "discount_factor": 1.0,
    "epsilon_decay": 0.999,
    "k": 500,
    "gaussian_width_rewards": 3.0,
    "training_seed": 1612431795,
    "testing_seed": 271423631,
    "comments": "",
    "training_time": 100,
    "testing_time": 100,
    "training_rewards": [
        27.0,
        36.0,
        8.0,
        10.0,
        59.0,
        43.0,
        37.0,
        35.0,
        31.0,
        37.0,
        41.0,
        48.0,
        53.0,
        73.0,
        40.0,
        41.0,
        52.0,
        42.0,
        39.0,
        48.0,
        135.0,
        39.0,
        70.0,
        134.0,
        55.0,
        124.0,
        73.0,
        92.0,
        157.0,
        97.0,
        66.0,
        16.0,
        93.0,
        105.0,
        33.0,
        59.0,
        213.0,
        11.0,
        43.0,
        42.0,
        52.0,
        50.0,
        19.0,
        15.0,
        177.0,
        392.0,
        55.0,
        62.0,
        108.0,
        131.0,
        108.0,
        79.0,
        145.0,
        237.0,
        137.0,
        127.0,
        236.0,
        323.0,
        21.0,
        169.0,
        167.0,
        212.0,
        168.0,
        157.0,
        256.0,
        44.0,
        154.0,
        160.0,
        122.0,
        38.0,
        220.0,
        377.0,
        197.0,
        164.0,
        252.0,
        108.0,
        236.0,
        270.0,
        67.0,
        39.0,
        134.0,
        330.0,
        147.0,
        245.0,
        178.0,
        151.0,
        213.0,
        199.0,
        63.0,
        204.0,
        122.0,
        259.0,
        42.0,
        199.0,
        165.0,
        189.0,
        45.0,
        252.0,
        253.0,
        181.0,
        423.0
    ],
    "testing_rewards": [
        33.0,
        35.0,
        28.0,
        29.0,
        29.0,
        40.0,
        35.0,
        36.0,
        36.0,
        35.0,
        33.0,
        37.0,
        36.0,
        27.0,
        33.0,
        42.0,
        35.0,
        38.0,
        30.0,
        27.0,
        31.0,
        38.0,
        41.0,
        37.0,
        28.0,
        40.0,
        41.0,
        41.0,
        32.0,
        34.0,
        39.0,
        41.0,
        38.0,
        31.0,
        30.0,
        38.0,
        39.0,
        41.0,
        35.0,
        36.0,
        47.0,
        31.0,
        42.0,
        34.0,
        41.0,
        31.0,
        38.0,
        30.0,
        34.0,
        33.0,
        34.0,
        32.0,
        34.0,
        33.0,
        40.0,
        26.0,
        32.0,
        41.0,
        35.0,
        36.0,
        34.0,
        34.0,
        35.0,
        29.0,
        33.0,
        43.0,
        35.0,
        36.0,
        40.0,
        29.0,
        29.0,
        35.0,
        36.0,
        30.0,
        42.0,
        39.0,
        39.0,
        42.0,
        35.0,
        41.0,
        29.0,
        35.0,
        36.0,
        36.0,
        39.0,
        41.0,
        41.0,
        37.0,
        29.0,
        41.0,
        33.0,
        33.0,
        35.0,
        39.0,
        32.0,
        45.0,
        36.0,
        32.0,
        43.0,
        34.0,
        35.0
    ]
}