{
    "environment": "CartPole-v1",
    "discount_factor": 1.0,
    "epsilon_decay": 0.999,
    "k": 3000,
    "gaussian_width_rewards": 1.0,
    "training_seed": 361545724,
    "testing_seed": 1863836132,
    "comments": "",
    "training_time": 100,
    "testing_time": 100,
    "training_rewards": [
        20.0,
        9.0,
        10.0,
        29.0,
        81.0,
        25.0,
        36.0,
        139.0,
        110.0,
        106.0,
        71.0,
        140.0,
        267.0,
        112.0,
        81.0,
        114.0,
        114.0,
        117.0,
        500.0,
        152.0,
        121.0,
        160.0,
        190.0,
        149.0,
        174.0,
        163.0,
        167.0,
        323.0,
        179.0,
        182.0,
        220.0,
        212.0,
        274.0,
        177.0,
        190.0,
        163.0,
        368.0,
        236.0,
        257.0,
        278.0,
        233.0,
        201.0,
        279.0,
        500.0,
        500.0,
        500.0,
        500.0,
        469.0,
        48.0,
        250.0,
        500.0,
        359.0,
        93.0,
        200.0,
        500.0,
        194.0,
        202.0,
        262.0,
        500.0,
        263.0,
        185.0,
        342.0,
        234.0,
        17.0,
        393.0,
        357.0,
        137.0,
        134.0,
        373.0,
        175.0,
        156.0,
        500.0,
        296.0,
        308.0,
        250.0,
        254.0,
        143.0,
        352.0,
        127.0,
        295.0,
        285.0,
        235.0,
        219.0,
        359.0,
        239.0,
        165.0,
        285.0,
        157.0,
        327.0,
        176.0,
        189.0,
        303.0,
        180.0,
        210.0,
        269.0,
        407.0,
        357.0,
        360.0,
        303.0,
        372.0,
        315.0
    ],
    "testing_rewards": [
        269.0,
        307.0,
        322.0,
        304.0,
        307.0,
        281.0,
        297.0,
        313.0,
        227.0,
        256.0,
        324.0,
        319.0,
        272.0,
        280.0,
        315.0,
        255.0,
        354.0,
        271.0,
        367.0,
        263.0,
        285.0,
        229.0,
        280.0,
        307.0,
        323.0,
        278.0,
        263.0,
        339.0,
        333.0,
        255.0,
        257.0,
        265.0,
        294.0,
        256.0,
        272.0,
        353.0,
        288.0,
        366.0,
        305.0,
        345.0,
        269.0,
        322.0,
        271.0,
        305.0,
        265.0,
        330.0,
        279.0,
        275.0,
        274.0,
        319.0,
        294.0,
        315.0,
        249.0,
        318.0,
        275.0,
        253.0,
        250.0,
        313.0,
        282.0,
        309.0,
        247.0,
        335.0,
        368.0,
        340.0,
        272.0,
        253.0,
        405.0,
        361.0,
        266.0,
        290.0,
        341.0,
        305.0,
        256.0,
        321.0,
        268.0,
        274.0,
        244.0,
        297.0,
        300.0,
        275.0,
        259.0,
        302.0,
        259.0,
        269.0,
        256.0,
        301.0,
        297.0,
        284.0,
        271.0,
        277.0,
        252.0,
        321.0,
        274.0,
        300.0,
        256.0,
        317.0,
        267.0,
        325.0,
        344.0,
        254.0,
        296.0
    ]
}