{
    "environment": "CartPole-v1",
    "discount_factor": 1.0,
    "epsilon_decay": 0.999,
    "k": 500,
    "gaussian_width_rewards": 2.5,
    "training_seed": 2735883094,
    "testing_seed": 2027423262,
    "comments": "",
    "training_time": 100,
    "testing_time": 100,
    "training_rewards": [
        11.0,
        12.0,
        10.0,
        13.0,
        10.0,
        25.0,
        60.0,
        58.0,
        42.0,
        41.0,
        46.0,
        54.0,
        108.0,
        80.0,
        151.0,
        28.0,
        67.0,
        72.0,
        127.0,
        178.0,
        53.0,
        85.0,
        94.0,
        103.0,
        97.0,
        47.0,
        48.0,
        49.0,
        49.0,
        50.0,
        39.0,
        63.0,
        157.0,
        63.0,
        86.0,
        151.0,
        57.0,
        72.0,
        90.0,
        184.0,
        99.0,
        140.0,
        86.0,
        99.0,
        146.0,
        89.0,
        113.0,
        97.0,
        110.0,
        500.0,
        500.0,
        101.0,
        173.0,
        172.0,
        55.0,
        237.0,
        271.0,
        82.0,
        65.0,
        107.0,
        363.0,
        68.0,
        186.0,
        12.0,
        146.0,
        11.0,
        50.0,
        141.0,
        239.0,
        99.0,
        105.0,
        43.0,
        76.0,
        98.0,
        214.0,
        337.0,
        149.0,
        126.0,
        321.0,
        192.0,
        45.0,
        123.0,
        124.0,
        92.0,
        98.0,
        320.0,
        13.0,
        170.0,
        114.0,
        220.0,
        102.0,
        125.0,
        170.0,
        122.0,
        156.0,
        305.0,
        224.0,
        169.0,
        317.0,
        339.0,
        324.0
    ],
    "testing_rewards": [
        16.0,
        18.0,
        12.0,
        14.0,
        14.0,
        17.0,
        15.0,
        15.0,
        16.0,
        17.0,
        12.0,
        17.0,
        17.0,
        14.0,
        17.0,
        12.0,
        18.0,
        17.0,
        18.0,
        16.0,
        17.0,
        17.0,
        15.0,
        14.0,
        17.0,
        14.0,
        16.0,
        15.0,
        17.0,
        16.0,
        13.0,
        12.0,
        15.0,
        18.0,
        13.0,
        16.0,
        15.0,
        15.0,
        12.0,
        12.0,
        13.0,
        11.0,
        18.0,
        16.0,
        15.0,
        14.0,
        14.0,
        14.0,
        14.0,
        17.0,
        16.0,
        13.0,
        18.0,
        16.0,
        14.0,
        12.0,
        17.0,
        17.0,
        14.0,
        12.0,
        15.0,
        12.0,
        15.0,
        13.0,
        15.0,
        17.0,
        14.0,
        13.0,
        18.0,
        13.0,
        17.0,
        12.0,
        14.0,
        16.0,
        17.0,
        15.0,
        17.0,
        14.0,
        12.0,
        14.0,
        17.0,
        12.0,
        14.0,
        16.0,
        13.0,
        12.0,
        18.0,
        15.0,
        12.0,
        19.0,
        16.0,
        18.0,
        13.0,
        19.0,
        13.0,
        18.0,
        12.0,
        15.0,
        16.0,
        12.0,
        12.0
    ]
}